dat_daemon_pyclient/__init__.py
dat_daemon_pyclient/client.py
dat_daemon_pyclient/daemon_pb2.py
dat_daemon_pyclient/sock.py
dat_daemon_pyclient-0.2.0.dist-info/LICENSE
dat_daemon_pyclient-0.2.0.dist-info/WHEEL
dat_daemon_pyclient-0.2.0.dist-info/METADATA
dat_daemon_pyclient-0.2.0.dist-info/RECORD
