Metadata-Version: 2.1
Name: dat-daemon-pyclient
Version: 0.2.0
Summary: a client for the dat-daemon
Home-page: https://framagit.org/synalp/olki/dat-daemon-pyclient
License: UNKNOWN
Author: Rigel Kent
Author-email: sendmemail@rigelk.eu
Requires-Python: >=3.7,<4.0
Classifier: Programming Language :: Python :: 3
Classifier: Programming Language :: Python :: 3.7
Requires-Dist: asyncio (>=3.4,<4.0)
Requires-Dist: grpcio-tools (>=1.18,<2.0)
Requires-Dist: protobuf (>=3.6,<4.0)
Requires-Dist: protobuf-to-dict
Requires-Dist: websockets (>=7.0,<8.0)
Project-URL: Repository, https://framagit.org/synalp/olki/dat-daemon-pyclient
